README.md
setup.cfg
setup.py
aurora/__init__.py
aurora/text_preprocessing/__init__.py
aurora/text_preprocessing/text.py
aurora_nlp.egg-info/PKG-INFO
aurora_nlp.egg-info/SOURCES.txt
aurora_nlp.egg-info/dependency_links.txt
aurora_nlp.egg-info/requires.txt
aurora_nlp.egg-info/top_level.txt
tests/__init__.py
tests/preprocessing/__init__.py
tests/preprocessing/test_text_preprocessing.py